{
  "name": "Macbook Air",
  "description": "O chip M1 da Apple revolucionou nosso notebook mais fino e leve. A CPU e a GPU estão mais rápidas, até 3,5 vezes e até cinco vezes, respectivamente. Nosso Neural Engine avançado deixa o aprendizado de máquina até nove vezes mais veloz. A bateria oferece mais tempo de duração. E trocamos a ventoinha pelo silêncio. Nunca tanto desempenho esteve reunido em um MacBook Air.",
  "inStock": 3,
  "price": 25000,
  "pictureUrl": "https://www.apple.com/v/macbook-air/n/images/overview/hero_endframe__ea0qze85eyi6_large.jpg"
}
